[
  { "id": 1,  "name": "Aurora Headphones",  "description": "Immersive sound with soft cushions and wireless freedom.",          "price": 26,  "imageUrl": "https://picsum.photos/400/300?random=1",  "rating": 4.3, "reviewCount": 18, "inStock": false, "category": "Audio" },
  { "id": 2,  "name": "Luna Watch",         "description": "Smart features and a polished look for everyday wear.",            "price": 33,  "imageUrl": "https://picsum.photos/400/300?random=2",  "rating": 4.4, "reviewCount": 21, "inStock": true,  "category": "Wearables" },
  { "id": 3,  "name": "Nova Backpack",      "description": "A lightweight backpack built for daily commute and travel.",       "price": 40,  "imageUrl": "https://picsum.photos/400/300?random=3",  "rating": 4.5, "reviewCount": 24, "inStock": true,  "category": "Accessories" },
  { "id": 4,  "name": "Orbit Lamp",         "description": "Modern ambient lighting that brightens any room.",                 "price": 47,  "imageUrl": "https://picsum.photos/400/300?random=4",  "rating": 4.6, "reviewCount": 27, "inStock": false, "category": "Home" },
  { "id": 5,  "name": "Pixel Camera",       "description": "Capture sharp details with a compact mirrorless setup.",          "price": 54,  "imageUrl": "https://picsum.photos/400/300?random=5",  "rating": 4.7, "reviewCount": 30, "inStock": true,  "category": "Photography" },
  { "id": 6,  "name": "Canyon Sneakers",    "description": "Lightweight comfort for city walks and weekend runs.",             "price": 61,  "imageUrl": "https://picsum.photos/400/300?random=6",  "rating": 4.8, "reviewCount": 33, "inStock": true,  "category": "Fashion" },
  { "id": 7,  "name": "Velvet Chair",       "description": "Soft upholstery and modern lines for a cozy workspace.",          "price": 68,  "imageUrl": "https://picsum.photos/400/300?random=7",  "rating": 4.3, "reviewCount": 36, "inStock": false, "category": "Furniture" },
  { "id": 8,  "name": "Drift Mug",          "description": "A ceramic mug designed for slow mornings and rich coffee.",        "price": 75,  "imageUrl": "https://picsum.photos/400/300?random=8",  "rating": 4.4, "reviewCount": 39, "inStock": true,  "category": "Kitchen" },
  { "id": 9,  "name": "Halo Speaker",       "description": "Clear sound and a premium finish for any room.",                  "price": 82,  "imageUrl": "https://picsum.photos/400/300?random=9",  "rating": 4.5, "reviewCount": 42, "inStock": true,  "category": "Audio" },
  { "id": 10, "name": "Silver Sleeve",      "description": "A slim sleeve to protect your laptop on the go.",                 "price": 89,  "imageUrl": "https://picsum.photos/400/300?random=10", "rating": 4.6, "reviewCount": 45, "inStock": false, "category": "Workspace" },
  { "id": 11, "name": "Echo Watch",         "description": "Smart features with a sleek daily look.",                         "price": 96,  "imageUrl": "https://picsum.photos/400/300?random=11", "rating": 4.7, "reviewCount": 48, "inStock": true,  "category": "Wearables" },
  { "id": 12, "name": "Summit Thermos",     "description": "Keeps drinks hot or cold for long days outdoors.",                "price": 103, "imageUrl": "https://picsum.photos/400/300?random=12", "rating": 4.8, "reviewCount": 51, "inStock": true,  "category": "Outdoors" },
  { "id": 13, "name": "Atlas Mat",          "description": "A smooth, durable surface for focused work sessions.",            "price": 110, "imageUrl": "https://picsum.photos/400/300?random=13", "rating": 4.3, "reviewCount": 54, "inStock": false, "category": "Fitness" },
  { "id": 14, "name": "Glow Light",         "description": "Soft lighting that makes every shot look professional.",          "price": 117, "imageUrl": "https://picsum.photos/400/300?random=14", "rating": 4.4, "reviewCount": 57, "inStock": true,  "category": "Home" },
  { "id": 15, "name": "Metro Tote",         "description": "Spacious and elegant for day-to-night use.",                     "price": 124, "imageUrl": "https://picsum.photos/400/300?random=15", "rating": 4.5, "reviewCount": 20, "inStock": true,  "category": "Fashion" },
  { "id": 16, "name": "Storm Earbuds",      "description": "Noise-reducing earbuds with long battery life.",                 "price": 131, "imageUrl": "https://picsum.photos/400/300?random=16", "rating": 4.6, "reviewCount": 23, "inStock": false, "category": "Audio" },
  { "id": 17, "name": "Indigo Notebook",    "description": "Premium paper for ideas, lists, and sketches.",                  "price": 138, "imageUrl": "https://picsum.photos/400/300?random=17", "rating": 4.7, "reviewCount": 26, "inStock": true,  "category": "Stationery" },
  { "id": 18, "name": "Orbit Monitor",      "description": "A crisp display for work, gaming, and creative tasks.",          "price": 145, "imageUrl": "https://picsum.photos/400/300?random=18", "rating": 4.8, "reviewCount": 29, "inStock": true,  "category": "Workspace" },
  { "id": 19, "name": "Pure Purifier",      "description": "Quiet filtration that refreshes your space.",                    "price": 152, "imageUrl": "https://picsum.photos/400/300?random=19", "rating": 4.3, "reviewCount": 32, "inStock": false, "category": "Home" },
  { "id": 20, "name": "Flex Case",          "description": "A rugged case that keeps essentials neatly organized.",          "price": 159, "imageUrl": "https://picsum.photos/400/300?random=20", "rating": 4.4, "reviewCount": 35, "inStock": true,  "category": "Tech" },
  { "id": 21, "name": "Solis Coffee Maker", "description": "Brew smooth coffee with a compact design.",                     "price": 166, "imageUrl": "https://picsum.photos/400/300?random=21", "rating": 4.5, "reviewCount": 38, "inStock": true,  "category": "Kitchen" },
  { "id": 22, "name": "Quill Set",          "description": "A refined writing set for notes and gifting.",                   "price": 173, "imageUrl": "https://picsum.photos/400/300?random=22", "rating": 4.6, "reviewCount": 41, "inStock": false, "category": "Stationery" },
  { "id": 23, "name": "Terra Pot",          "description": "Bring warmth and style to your favorite indoor plants.",         "price": 180, "imageUrl": "https://picsum.photos/400/300?random=23", "rating": 4.7, "reviewCount": 44, "inStock": true,  "category": "Home" },
  { "id": 24, "name": "Zen Mat",            "description": "A cushioned mat for mindful movement and recovery.",             "price": 187, "imageUrl": "https://picsum.photos/400/300?random=24", "rating": 4.8, "reviewCount": 47, "inStock": true,  "category": "Fitness" },
  { "id": 25, "name": "Aero Keyboard",      "description": "Responsive keys with a slim profile for modern setups.",        "price": 194, "imageUrl": "https://picsum.photos/400/300?random=25", "rating": 4.3, "reviewCount": 50, "inStock": false, "category": "Workspace" },
  { "id": 26, "name": "Cobalt Mouse",       "description": "Comfortable grip and precise tracking for all-day use.",        "price": 201, "imageUrl": "https://picsum.photos/400/300?random=26", "rating": 4.4, "reviewCount": 53, "inStock": true,  "category": "Tech" },
  { "id": 27, "name": "Vivid Cushion",      "description": "A plush accent piece that feels soft and modern.",              "price": 208, "imageUrl": "https://picsum.photos/400/300?random=27", "rating": 4.5, "reviewCount": 56, "inStock": true,  "category": "Home" },
  { "id": 28, "name": "Lumen Lamp",         "description": "Adjustable brightness for work and reading.",                   "price": 215, "imageUrl": "https://picsum.photos/400/300?random=28", "rating": 4.6, "reviewCount": 19, "inStock": false, "category": "Home" },
  { "id": 29, "name": "Ridge Bottle",       "description": "Durable hydration with a sleek insulated body.",                "price": 222, "imageUrl": "https://picsum.photos/400/300?random=29", "rating": 4.7, "reviewCount": 22, "inStock": true,  "category": "Outdoors" },
  { "id": 30, "name": "Drift Grip",         "description": "A secure phone grip that feels great in every hand.",           "price": 229, "imageUrl": "https://picsum.photos/400/300?random=30", "rating": 4.8, "reviewCount": 25, "inStock": true,  "category": "Accessories" },
  { "id": 31, "name": "Swift Charger",      "description": "Fast charging with a compact travel-ready design.",             "price": 236, "imageUrl": "https://picsum.photos/400/300?random=31", "rating": 4.3, "reviewCount": 28, "inStock": false, "category": "Tech" },
  { "id": 32, "name": "Ivy Planner",        "description": "A minimalist planner for your weekly routine.",                 "price": 243, "imageUrl": "https://picsum.photos/400/300?random=32", "rating": 4.4, "reviewCount": 31, "inStock": true,  "category": "Stationery" },
  { "id": 33, "name": "North Hoodie",       "description": "A soft everyday layer made for comfort and style.",             "price": 250, "imageUrl": "https://picsum.photos/400/300?random=33", "rating": 4.5, "reviewCount": 34, "inStock": true,  "category": "Fashion" },
  { "id": 34, "name": "Bloom Vase",         "description": "A sculpted vase that elevates fresh flowers and greens.",       "price": 257, "imageUrl": "https://picsum.photos/400/300?random=34", "rating": 4.6, "reviewCount": 37, "inStock": false, "category": "Home" },
  { "id": 35, "name": "Flint Knife",        "description": "Sharp tools for everyday cooking prep.",                        "price": 264, "imageUrl": "https://picsum.photos/400/300?random=35", "rating": 4.7, "reviewCount": 40, "inStock": true,  "category": "Kitchen" },
  { "id": 36, "name": "Sora Stand",         "description": "A sturdy stand that keeps your tablet at the perfect angle.",  "price": 271, "imageUrl": "https://picsum.photos/400/300?random=36", "rating": 4.8, "reviewCount": 43, "inStock": true,  "category": "Tech" },
  { "id": 37, "name": "Wave Headset",       "description": "A comfortable headset for calls, playlists, and gaming.",      "price": 278, "imageUrl": "https://picsum.photos/400/300?random=37", "rating": 4.3, "reviewCount": 46, "inStock": false, "category": "Audio" },
  { "id": 38, "name": "Echo Mini",          "description": "Portable sound with a clear bass response.",                   "price": 285, "imageUrl": "https://picsum.photos/400/300?random=38", "rating": 4.4, "reviewCount": 49, "inStock": true,  "category": "Audio" },
  { "id": 39, "name": "Summit Runner",      "description": "Responsive cushioning for miles of comfort.",                  "price": 292, "imageUrl": "https://picsum.photos/400/300?random=39", "rating": 4.5, "reviewCount": 52, "inStock": true,  "category": "Fashion" },
  { "id": 40, "name": "Aura Perfume",       "description": "A fresh fragrance with a clean modern feel.",                  "price": 299, "imageUrl": "https://picsum.photos/400/300?random=40", "rating": 4.6, "reviewCount": 55, "inStock": false, "category": "Beauty" },
  { "id": 41, "name": "Glacier Cooler",     "description": "Keep snacks and drinks fresh on every trip.",                  "price": 306, "imageUrl": "https://picsum.photos/400/300?random=41", "rating": 4.7, "reviewCount": 18, "inStock": true,  "category": "Outdoors" },
  { "id": 42, "name": "Canvas Tote",        "description": "A roomy tote for everyday errands and weekend plans.",         "price": 313, "imageUrl": "https://picsum.photos/400/300?random=42", "rating": 4.8, "reviewCount": 21, "inStock": true,  "category": "Fashion" },
  { "id": 43, "name": "Pixel Bag",          "description": "Compact storage with a stylish protective silhouette.",        "price": 320, "imageUrl": "https://picsum.photos/400/300?random=43", "rating": 4.3, "reviewCount": 24, "inStock": false, "category": "Accessories" },
  { "id": 44, "name": "Hush Earbuds",       "description": "Lightweight earbuds with rich sound and comfort.",             "price": 327, "imageUrl": "https://picsum.photos/400/300?random=44", "rating": 4.4, "reviewCount": 27, "inStock": true,  "category": "Audio" },
  { "id": 45, "name": "Solar Bank",         "description": "Portable charging power that keeps your devices ready.",       "price": 334, "imageUrl": "https://picsum.photos/400/300?random=45", "rating": 4.5, "reviewCount": 30, "inStock": true,  "category": "Tech" },
  { "id": 46, "name": "Cedar Throw",        "description": "A soft throw blanket for cozy evenings and weekends.",         "price": 341, "imageUrl": "https://picsum.photos/400/300?random=46", "rating": 4.6, "reviewCount": 33, "inStock": false, "category": "Home" },
  { "id": 47, "name": "Pacer Bottle",       "description": "Easy-carry hydration with a modern silhouette.",               "price": 348, "imageUrl": "https://picsum.photos/400/300?random=47", "rating": 4.7, "reviewCount": 36, "inStock": true,  "category": "Outdoors" },
  { "id": 48, "name": "Slate Organizer",    "description": "Keep your desk tidy with smart compartments and style.",       "price": 355, "imageUrl": "https://picsum.photos/400/300?random=48", "rating": 4.8, "reviewCount": 39, "inStock": true,  "category": "Workspace" },
  { "id": 49, "name": "Comet Clock",        "description": "A modern desk clock that adds practical charm.",               "price": 362, "imageUrl": "https://picsum.photos/400/300?random=49", "rating": 4.3, "reviewCount": 42, "inStock": false, "category": "Home" },
  { "id": 50, "name": "Velvet Runner",      "description": "A stylish sneaker designed for comfort and all-day wear.",     "price": 369, "imageUrl": "https://picsum.photos/400/300?random=50", "rating": 4.4, "reviewCount": 45, "inStock": true,  "category": "Fashion" }
]
